sphinxcolor/__init__.py
sphinxcolor/__main__.py
sphinxcolor/__version__.py
sphinxcolor/colorizer.py
sphinxcolor/config.py
sphinxcolor/extension.py
sphinxcolor/sphinxcolor.toml
sphinxcolor-0.1.4.dist-info/licenses/LICENSE
sphinxcolor-0.1.4.dist-info/METADATA
sphinxcolor-0.1.4.dist-info/WHEEL
sphinxcolor-0.1.4.dist-info/entry_points.txt
sphinxcolor-0.1.4.dist-info/top_level.txt
sphinxcolor-0.1.4.dist-info/RECORD
