Metadata-Version: 2.4
Name: sphinxcolor
Version: 0.1.4
Summary: Colorize Sphinx build output with customizable colors
Home-page: https://github.com/cumulus13/sphinxcolor
Author: Hadi Cahyadi
Author-email: Hadi Cahyadi <cumulus13@gmail.com>
License-Expression: MIT
Project-URL: Homepage, https://github.com/cumulus13/sphinxcolor
Project-URL: Bug Reports, https://github.com/cumulus13/sphinxcolor/issues
Project-URL: Source, https://github.com/cumulus13/sphinxcolor
Project-URL: Documentation, https://github.com/cumulus13/sphinxcolor/blob/main/README.md
Keywords: sphinx,documentation,color,colorize,rich,terminal
Classifier: Development Status :: 4 - Beta
Classifier: Intended Audience :: Developers
Classifier: Topic :: Documentation
Classifier: Topic :: Software Development :: Documentation
Classifier: Programming Language :: Python :: 3
Classifier: Programming Language :: Python :: 3.7
Classifier: Programming Language :: Python :: 3.8
Classifier: Programming Language :: Python :: 3.9
Classifier: Programming Language :: Python :: 3.10
Classifier: Programming Language :: Python :: 3.11
Classifier: Programming Language :: Python :: 3.12
Classifier: Framework :: Sphinx :: Extension
Requires-Python: >=3.7
License-File: LICENSE
Requires-Dist: rich>=13.0.0
Requires-Dist: tomli>=2.0.0
Provides-Extra: dev
Requires-Dist: pytest>=6.0; extra == "dev"
Requires-Dist: pytest-cov; extra == "dev"
Requires-Dist: black; extra == "dev"
Requires-Dist: flake8; extra == "dev"
Requires-Dist: mypy; extra == "dev"
Provides-Extra: sphinx
Requires-Dist: sphinx>=3.0; extra == "sphinx"
Dynamic: author
Dynamic: home-page
Dynamic: license-file
Dynamic: requires-python
